{
  "higher_level": [],
  "index": "telekinesis",
  "name": "Télékinésie",
  "desc": [
    "Vous gagnez la capacité de déplacer ou de manipuler des créatures ou des objets par la pensée. Lorsque vous lancez le sort, et lors de votre action à chaque tour pendant toute la durée du sort, vous pouvez exercer votre volonté sur une créature ou un objet que vous pouvez voir à portée, provoquant l'effet approprié ci-dessous. Vous pouvez affecter la même cible tour après tour, ou en choisir une nouvelle à tout moment. Si vous changez de cible, la cible précédente n'est plus affectée par le sort.\n***Créature.*** Vous pouvez essayer de déplacer une créature de taille énorme ou plus petite. Effectuez un test de capacité avec votre capacité de lancement de sorts contestée par le test de Force de la créature. Si vous gagnez le concours, vous déplacez la créature jusqu'à 9 m/ 30 ftètres dans n'importe quelle direction, y compris vers le haut, mais pas au-delà de la portée de ce sort. Jusqu'à la fin de votre prochain tour, la créature est retenue par votre emprise télékinésique. Une créature soulevée vers le haut est suspendue dans les airs.\nLors des tours suivants, vous pouvez utiliser votre action pour tenter de maintenir votre emprise télékinésique sur la créature en répétant le concours.\n***Objet.*** Vous pouvez essayer de déplacer un objet pesant jusqu'à 1 000 livres. Si l'objet n'est pas porté ou transporté, vous le déplacez automatiquement jusqu'à 9 m/ 30 ftètres dans n'importe quelle direction, mais pas au-delà de la portée de ce sort.\nSi l'objet est porté ou transporté par une créature, vous devez effectuer un test de capacité avec votre capacité de lancement de sorts contestée par le test de Force de cette créature. Si vous réussissez, vous éloignez l'objet de cette créature et pouvez le déplacer jusqu'à 9 m/ 30 ftètres dans n'importe quelle direction, mais pas au-delà de la portée de ce sort.\nVous pouvez exercer un contrôle précis sur des objets grâce à votre poignée télékinésique, comme manipuler un outil simple, ouvrir une porte ou un conteneur, ranger ou récupérer un objet dans un conteneur ouvert ou verser le contenu d'un flacon."
  ],
  "range": "60 pieds",
  "components": [
    "V",
    "S"
  ],
  "ritual": false,
  "duration": "Jusqu'à 10 minutes",
  "concentration": true,
  "casting_time": "1 action",
  "level": 5,
  "area_of_effect": {
    "type": "sphere",
    "size": 30
  },
  "school": {
    "index": "transmutation",
    "name": "Transmutation",
    "url": "/api/2014/magic-schools/transmutation",
    "name_fr": "Transmutation"
  },
  "classes": [
    {
      "index": "sorcerer",
      "name": "Sorcerer",
      "url": "/api/2014/classes/sorcerer"
    },
    {
      "index": "wizard",
      "name": "Wizard",
      "url": "/api/2014/classes/wizard"
    }
  ],
  "subclasses": [],
  "url": "/api/2014/spells/telekinesis",
  "updated_at": "2025-10-24T20:42:14.619Z",
  "name_en": "Telekinesis",
  "material": "",
  "_translated": true
}