{
  "higher_level": [],
  "index": "hallow",
  "name": "Sanctifier",
  "desc": [
    "Vous touchez un point et imprègnez une zone autour de lui d’un pouvoir sacré (ou impie). La zone peut avoir un rayon allant jusqu'à 60 pieds, et le sort échoue si le rayon inclut une zone déjà sous l'effet d'un sort sacré. La zone affectée est soumise aux effets suivants.\nPremièrement, les célestes, les élémentaires, les fées, les démons et les morts-vivants ne peuvent pas entrer dans la zone, et ces créatures ne peuvent pas non plus charmer, effrayer ou posséder des créatures à l'intérieur. Toute créature charmée, effrayée ou possédée par une telle créature n'est plus charmée, effrayée ou possédée en entrant dans la zone. Vous pouvez exclure un ou plusieurs de ces types de créatures de cet effet.\nDeuxièmement, vous pouvez lier un effet supplémentaire à la zone. Choisissez l'effet dans la liste suivante, ou choisissez un effet proposé par le MJ. Certains de ces effets s'appliquent aux créatures de la zone ; vous pouvez indiquer si l'effet s'applique à toutes les créatures, aux créatures qui suivent une divinité ou un chef spécifique, ou aux créatures d'un type spécifique, comme les minerais ou les trolls. Lorsqu'une créature qui serait affectée entre dans la zone du sort pour la première fois d'un tour ou y commence son tour, elle peut effectuer un jet de sauvegarde de charisme. En cas de réussite, la créature ignore l'effet supplémentaire jusqu'à ce qu'elle quitte la zone.\n***Courage.*** Les créatures affectées ne peuvent pas être effrayées lorsqu'elles se trouvent dans la zone.\n***Obscurité.*** L'obscurité remplit la zone. La lumière normale, ainsi que la lumière magique créée par des sorts d'un niveau inférieur à celui de l'emplacement que vous avez utilisé pour lancer ce sort, ne peuvent pas éclairer la zone.\n*** Lumière du jour. *** Une lumière vive remplit la zone. Les ténèbres magiques créées par des sorts d'un niveau inférieur à celui de l'emplacement que vous avez utilisé pour lancer ce sort ne peuvent pas éteindre la lumière.\n***Protection énergétique.*** Les créatures affectées dans la zone ont une résistance à un type de dégâts de votre choix, à l'exception des contondants, des perforants ou des tranches.\n***Vulnérabilité énergétique.*** Les créatures affectées dans la zone sont vulnérables à un type de dégâts de votre choix, à l'exception des dégâts contondants, perçants ou tranchants.\n***Repos éternel.*** Les cadavres enterrés dans la zone ne peuvent pas être transformés en morts-vivants.\n***Interférence extradimensionnelle.*** Les créatures affectées ne peuvent pas se déplacer ou voyager par téléportation ou par des moyens extradimensionnels ou interplanaires.\n***Peur.*** Les créatures affectées sont effrayées lorsqu'elles se trouvent dans la zone.\n***Silence.*** Aucun son ne peut émaner de la zone, et aucun son ne peut y pénétrer.\n***Langues.*** Les créatures affectées peuvent communiquer avec n'importe quelle autre créature de la zone, même si elles ne partagent pas une langue commune."
  ],
  "range": "Touche",
  "components": [
    "V",
    "S",
    "M"
  ],
  "material": "Herbes, huiles et encens d'une valeur d'au moins 1 000 po, que le sort consomme.",
  "ritual": false,
  "duration": "Jusqu'à ce qu'il soit dissipé",
  "concentration": false,
  "casting_time": "24 heures",
  "level": 5,
  "dc": {
    "dc_type": {
      "index": "cha",
      "name": "CHA",
      "url": "/api/2014/ability-scores/cha"
    },
    "dc_success": "none"
  },
  "area_of_effect": {
    "type": "sphere",
    "size": 60
  },
  "school": {
    "index": "evocation",
    "name": "Evocation",
    "url": "/api/2014/magic-schools/evocation",
    "name_fr": "Évocation"
  },
  "classes": [
    {
      "index": "cleric",
      "name": "Cleric",
      "url": "/api/2014/classes/cleric"
    }
  ],
  "subclasses": [
    {
      "index": "fiend",
      "name": "Fiend",
      "url": "/api/2014/subclasses/fiend"
    }
  ],
  "url": "/api/2014/spells/hallow",
  "updated_at": "2025-10-24T20:42:14.619Z",
  "name_en": "Hallow",
  "_translated": true
}