{
  "index": "sailor",
  "name": "Background: Sailor",
  "source": "Player's Handbook",
  "desc": "You sailed on a seagoing vessel for years. In that time, you faced down mighty storms, monsters of the deep, and those who wanted to sink your craft to the bottomless depths. Your first love is the distant line of the horizon, but the time has come to try your hand at something new.\n\nDiscuss the nature of the ship you previously sailed with your DM. Was it a merchant ship, a naval vessel, a ship of discovery, or a pirate ship? How famous (or infamous) is it? Is it widely traveled? Is it still sailing, or is it missing and presumed lost with all hands?\n\nWhat were your duties on board – boatswain, captain, navigator, cook, or some other position? Who were the captain and first mate? Did you leave your ship on good terms with your fellows, or on the run?\n\nSkill Proficiencies: Athletics, Perception\nTool Proficiencies: Navigator's tools, vehicles (water)\nLanguages: None\nEquipment: A belaying pin (clubValue:1sp Weight:2lbs), 50 feet of silk ropeValue:10gp Weight:5lbs, a lucky charm such as a rabbit foot or a small stone with a hole in the center (or you may roll for a random trinket on the Trinkets table in chapter 5), a set of common clothesValue:5sp Weight:3lbs, and a pouchValue:5sp Weight:1lb containing 10gp",
  "skill_proficiencies": [
    "Athletics",
    "Perception\nTool Proficiencies: Navigator's tools",
    "vehicles (water)\nLanguages: None\nEquipment: A belaying pin (clubValue:1sp Weight:2lbs)",
    "50 feet of silk ropeValue:10gp Weight:5lbs",
    "a lucky charm such as a rabbit foot or a small stone with a hole in the center (or you may roll for a random trinket on the Trinkets table in chapter 5)",
    "a set of common clothesValue:5sp Weight:3lbs",
    "and a pouchValue:5sp Weight:1lb containing 10gp"
  ],
  "feature": null
}